huggingface_tool/__init__.py
huggingface_tool/cli/__init__.py
huggingface_tool/cli/cli.py
huggingface_tool/savers/__init__.py
huggingface_tool/savers/base_api_saver.py
huggingface_tool/savers/base_model_saver.py
huggingface_tool/savers/base_saver.py
huggingface_tool/savers/dataset_saver.py
huggingface_tool/savers/diffusion_model_saver.py
huggingface_tool/savers/file_saver.py
huggingface_tool/savers/model_saver.py
huggingface_tool/savers/repo_saver.py
huggingface_tool/savers/tokenizer_saver.py
huggingface_tool/uploaders/__init__.py
huggingface_tool/uploaders/base_api_uploader.py
huggingface_tool/uploaders/base_uploader.py
huggingface_tool/uploaders/dataset_uploader.py
huggingface_tool/uploaders/dir_uploader.py
huggingface_tool/uploaders/file_uploader.py
huggingface_tool/uploaders/model_uploader.py
huggingface_tool/uploaders/utils.py
huggingface_tool/utils/__init__.py
huggingface_tool/utils/logger.py
huggingface_tool/utils/util.py
huggingface_tool-0.0.6.dist-info/LICENSE
huggingface_tool-0.0.6.dist-info/METADATA
huggingface_tool-0.0.6.dist-info/WHEEL
huggingface_tool-0.0.6.dist-info/entry_points.txt
huggingface_tool-0.0.6.dist-info/top_level.txt
huggingface_tool-0.0.6.dist-info/RECORD
